{"credit":"Originally created by GamerKM. Optimized.","textures":{"hardened_clay_blue":"block/blue_terracotta","wool_lime":"block/lime_wool","hardened_clay_red":"block/red_terracotta","quartz_block":"block/quartz_block_bottom","stone_stab":"block/smooth_stone","coal_block":"block/coal_block"},"elements":[{"from":[-5.5,5.5,10],"to":[-1,8,10.5],"faces":{"north":{"uv":[1,8,5.5,10.5],"texture":"#hardened_clay_blue"},"south":{"uv":[10.5,8,15,10.5],"texture":"#hardened_clay_blue"},"down":{"uv":[10.5,5.5,15,6],"texture":"#hardened_clay_blue"}}},{"from":[4.5,9,10],"to":[7,11,11],"faces":{"north":{"uv":[0,9,1,10],"texture":"#wool_lime"},"east":{"uv":[0,9,1,10],"texture":"#wool_lime"},"south":{"uv":[0,9,1,10],"texture":"#wool_lime"},"up":{"uv":[0,9,1,10],"texture":"#wool_lime"}}},{"from":[2.5,8.5,10],"to":[3.5,9.5,10.5],"faces":{"north":{"uv":[0,9,1,10],"texture":"#hardened_clay_red"},"south":{"uv":[0,9,1,10],"texture":"#hardened_clay_red"}}},{"from":[3,9.5,10],"to":[4,10.5,10.5],"faces":{"north":{"uv":[0,9,1,10],"texture":"#hardened_clay_red"},"south":{"uv":[0,9,1,10],"texture":"#hardened_clay_red"}}},{"from":[3.5,10.5,10],"to":[4,11.5,10.5],"faces":{"north":{"uv":[0,9,1,10],"texture":"#hardened_clay_red"},"east":{"uv":[0,9,1,10],"texture":"#hardened_clay_red"},"south":{"uv":[0,9,1,10],"texture":"#hardened_clay_red"},"west":{"uv":[0,9,1,10],"texture":"#hardened_clay_red"},"up":{"uv":[0,9,1,10],"texture":"#hardened_clay_red"}}},{"from":[6,11,10],"to":[7,12,11],"faces":{"north":{"uv":[0,9,1,10],"texture":"#wool_lime"},"east":{"uv":[0,9,1,10],"texture":"#wool_lime"},"south":{"uv":[0,9,1,10],"texture":"#wool_lime"},"west":{"uv":[0,9,1,10],"texture":"#wool_lime"},"up":{"uv":[0,9,1,10],"texture":"#wool_lime"}}},{"from":[4,6,10],"to":[4.5,11,11],"faces":{"north":{"uv":[0,9,1,10],"texture":"#quartz_block"},"south":{"uv":[0,9,1,10],"texture":"#quartz_block"},"west":{"uv":[0,9,1,10],"texture":"#quartz_block"},"up":{"uv":[0,9,1,10],"texture":"#quartz_block"},"down":{"uv":[0,9,1,10],"texture":"#quartz_block"}}},{"from":[5,11,10],"to":[6,11.5,11],"faces":{"north":{"uv":[0,9,1,10],"texture":"#wool_lime"},"south":{"uv":[0,9,1,10],"texture":"#wool_lime"},"west":{"uv":[0,9,1,10],"texture":"#wool_lime"},"up":{"uv":[0,9,1,10],"texture":"#wool_lime"}}},{"from":[5,7,10],"to":[7,9,11.5],"faces":{"north":{"uv":[0,9,1,10],"texture":"#wool_lime"},"east":{"uv":[0,9,1,10],"texture":"#wool_lime"},"south":{"uv":[0,9,1,10],"texture":"#wool_lime"},"west":{"uv":[0,9,1,10],"texture":"#wool_lime"},"down":{"uv":[0,9,1,10],"texture":"#wool_lime"}}},{"from":[5.5,5.5,10],"to":[7,7,11.5],"faces":{"north":{"uv":[0,9,1,10],"texture":"#wool_lime"},"east":{"uv":[0,9,1,10],"texture":"#wool_lime"},"south":{"uv":[0,9,1,10],"texture":"#wool_lime"},"west":{"uv":[0,9,1,10],"texture":"#wool_lime"},"down":{"uv":[0,9,1,10],"texture":"#wool_lime"}}},{"from":[6,4.5,10],"to":[7,5.5,11.5],"faces":{"north":{"uv":[0,9,1,10],"texture":"#wool_lime"},"east":{"uv":[0,9,1,10],"texture":"#wool_lime"},"south":{"uv":[0,9,1,10],"texture":"#wool_lime"},"west":{"uv":[0,9,1,10],"texture":"#wool_lime"},"down":{"uv":[0,9,1,10],"texture":"#wool_lime"}}},{"from":[6.5,3.5,10],"to":[7,4.5,11],"faces":{"north":{"uv":[0,9,1,10],"texture":"#wool_lime"},"east":{"uv":[0,9,1,10],"texture":"#wool_lime"},"south":{"uv":[0,9,1,10],"texture":"#wool_lime"}}},{"from":[9,11,10],"to":[10,12,11],"faces":{"north":{"uv":[0,9,1,10],"texture":"#wool_lime"},"east":{"uv":[0,9,1,10],"texture":"#wool_lime"},"south":{"uv":[0,9,1,10],"texture":"#wool_lime"},"west":{"uv":[0,9,1,10],"texture":"#wool_lime"},"up":{"uv":[0,9,1,10],"texture":"#wool_lime"}}},{"from":[10,11,10],"to":[11,11.5,11],"faces":{"north":{"uv":[0,9,1,10],"texture":"#wool_lime"},"east":{"uv":[0,9,1,10],"texture":"#wool_lime"},"south":{"uv":[0,9,1,10],"texture":"#wool_lime"},"up":{"uv":[0,9,1,10],"texture":"#wool_lime"}}},{"from":[9,9,10],"to":[11.5,11,11],"faces":{"north":{"uv":[0,9,1,10],"texture":"#wool_lime"},"south":{"uv":[0,9,1,10],"texture":"#wool_lime"},"west":{"uv":[0,9,1,10],"texture":"#wool_lime"},"up":{"uv":[0,9,1,10],"texture":"#wool_lime"}}},{"from":[9,7,10],"to":[11,9,11.5],"faces":{"north":{"uv":[0,9,1,10],"texture":"#wool_lime"},"east":{"uv":[0,9,1,10],"texture":"#wool_lime"},"south":{"uv":[0,9,1,10],"texture":"#wool_lime"},"west":{"uv":[0,9,1,10],"texture":"#wool_lime"},"down":{"uv":[0,9,1,10],"texture":"#wool_lime"}}},{"from":[9,5.5,10],"to":[10.5,7,11.5],"faces":{"north":{"uv":[0,9,1,10],"texture":"#wool_lime"},"east":{"uv":[0,9,1,10],"texture":"#wool_lime"},"south":{"uv":[0,9,1,10],"texture":"#wool_lime"},"west":{"uv":[0,9,1,10],"texture":"#wool_lime"},"down":{"uv":[0,9,1,10],"texture":"#wool_lime"}}},{"from":[9,4.5,10],"to":[10,5.5,11.5],"faces":{"north":{"uv":[0,9,1,10],"texture":"#wool_lime"},"east":{"uv":[0,9,1,10],"texture":"#wool_lime"},"south":{"uv":[0,9,1,10],"texture":"#wool_lime"},"west":{"uv":[0,9,1,10],"texture":"#wool_lime"},"down":{"uv":[0,9,1,10],"texture":"#wool_lime"}}},{"from":[9,3.5,10],"to":[9.5,4.5,11],"faces":{"north":{"uv":[0,9,1,10],"texture":"#wool_lime"},"south":{"uv":[0,9,1,10],"texture":"#wool_lime"},"west":{"uv":[0,9,1,10],"texture":"#wool_lime"}}},{"from":[11.5,6,10],"to":[12,11,11],"faces":{"north":{"uv":[0,9,1,10],"texture":"#quartz_block"},"east":{"uv":[0,9,1,10],"texture":"#quartz_block"},"south":{"uv":[0,9,1,10],"texture":"#quartz_block"},"up":{"uv":[0,9,1,10],"texture":"#quartz_block"},"down":{"uv":[0,9,1,10],"texture":"#quartz_block"}}},{"from":[11,4.5,10],"to":[11.5,9,11],"faces":{"north":{"uv":[0,9,1,10],"texture":"#quartz_block"},"east":{"uv":[0,9,1,10],"texture":"#quartz_block"},"south":{"uv":[0,9,1,10],"texture":"#quartz_block"}}},{"from":[4.5,4.5,10],"to":[5,9,11],"faces":{"north":{"uv":[0,9,1,10],"texture":"#quartz_block"},"south":{"uv":[0,9,1,10],"texture":"#quartz_block"},"west":{"uv":[0,9,1,10],"texture":"#quartz_block"}}},{"from":[5,3,10],"to":[7,3.5,11],"faces":{"north":{"uv":[0,9,1,10],"texture":"#quartz_block"},"east":{"uv":[0,9,1,10],"texture":"#quartz_block"},"south":{"uv":[0,9,1,10],"texture":"#quartz_block"},"west":{"uv":[0,9,1,10],"texture":"#quartz_block"}}},{"from":[4.5,3.5,10],"to":[6.5,4.5,11],"faces":{"north":{"uv":[0,9,1,10],"texture":"#quartz_block"},"south":{"uv":[0,9,1,10],"texture":"#quartz_block"},"west":{"uv":[0,9,1,10],"texture":"#quartz_block"},"down":{"uv":[0,9,1,10],"texture":"#quartz_block"}}},{"from":[5,4.5,10],"to":[6,5.5,11],"faces":{"north":{"uv":[0,9,1,10],"texture":"#quartz_block"},"south":{"uv":[0,9,1,10],"texture":"#quartz_block"}}},{"from":[5,5.5,10],"to":[5.5,7,11],"faces":{"north":{"uv":[0,9,1,10],"texture":"#quartz_block"},"south":{"uv":[0,9,1,10],"texture":"#quartz_block"}}},{"from":[9.5,3.5,10],"to":[11.5,4.5,11],"faces":{"north":{"uv":[0,9,1,10],"texture":"#quartz_block"},"east":{"uv":[0,9,1,10],"texture":"#quartz_block"},"south":{"uv":[0,9,1,10],"texture":"#quartz_block"},"down":{"uv":[0,9,1,10],"texture":"#quartz_block"}}},{"from":[9,3,10],"to":[11,3.5,11],"faces":{"north":{"uv":[0,9,1,10],"texture":"#quartz_block"},"east":{"uv":[0,9,1,10],"texture":"#quartz_block"},"south":{"uv":[0,9,1,10],"texture":"#quartz_block"},"west":{"uv":[0,9,1,10],"texture":"#quartz_block"}}},{"from":[10.5,5.5,10],"to":[11,7,11],"faces":{"north":{"uv":[0,9,1,10],"texture":"#quartz_block"},"south":{"uv":[0,9,1,10],"texture":"#quartz_block"}}},{"from":[10,4.5,10],"to":[11,5.5,11],"faces":{"north":{"uv":[0,9,1,10],"texture":"#quartz_block"},"south":{"uv":[0,9,1,10],"texture":"#quartz_block"}}},{"from":[7.5,2.5,10.5],"to":[8.5,3,11],"faces":{"east":{"uv":[5,13,5.5,13.5],"texture":"#hardened_clay_blue"},"south":{"uv":[7.5,13,8.5,13.5],"texture":"#hardened_clay_blue"},"west":{"uv":[10.5,13,11,13.5],"texture":"#hardened_clay_blue"},"down":{"uv":[7.5,5,8.5,5.5],"texture":"#hardened_clay_blue"}}},{"from":[7,3,10.5],"to":[9,5.5,11],"faces":{"north":{"uv":[7,10.5,9,13],"texture":"#hardened_clay_blue"},"south":{"uv":[7,10.5,9,13],"texture":"#hardened_clay_blue"},"down":{"uv":[7,5,9,5.5],"texture":"#hardened_clay_blue"}}},{"from":[7.5,6.5,10.5],"to":[8.5,7,11],"faces":{"north":{"uv":[7.5,9,8.5,9.5],"texture":"#hardened_clay_blue"},"south":{"uv":[7.5,9,8.5,9.5],"texture":"#hardened_clay_blue"}}},{"from":[7,7,10.5],"to":[9,9.5,11],"faces":{"north":{"uv":[0,9,1,10],"texture":"#quartz_block"},"south":{"uv":[0,9,1,10],"texture":"#quartz_block"}}},{"from":[7,6.5,10.5],"to":[7.5,7,11],"faces":{"north":{"uv":[0,9,1,10],"texture":"#quartz_block"},"south":{"uv":[0,9,1,10],"texture":"#quartz_block"}}},{"from":[8.5,6.5,10.5],"to":[9,7,11],"faces":{"north":{"uv":[0,9,1,10],"texture":"#quartz_block"},"south":{"uv":[0,9,1,10],"texture":"#quartz_block"}}},{"from":[7,9.5,10.5],"to":[7.5,10,11],"faces":{"north":{"uv":[0,9,1,10],"texture":"#quartz_block"},"south":{"uv":[0,9,1,10],"texture":"#quartz_block"}}},{"from":[8.5,9.5,10.5],"to":[9,10,11],"faces":{"north":{"uv":[0,9,1,10],"texture":"#quartz_block"},"south":{"uv":[0,9,1,10],"texture":"#quartz_block"}}},{"from":[7.5,9.5,10.5],"to":[8.5,10.5,11],"faces":{"north":{"uv":[7.5,5.5,8.5,6.5],"texture":"#hardened_clay_blue"},"south":{"uv":[7.5,5.5,8.5,6.5],"texture":"#hardened_clay_blue"},"up":{"uv":[7.5,10.5,8.5,11],"texture":"#hardened_clay_blue"}}},{"from":[7,10.5,10],"to":[9,11,10.5],"faces":{"north":{"uv":[0,9,1,10],"texture":"#quartz_block"},"south":{"uv":[0,9,1,10],"texture":"#quartz_block"},"up":{"uv":[0,9,1,10],"texture":"#quartz_block"},"down":{"uv":[0,9,1,10],"texture":"#quartz_block"}}},{"from":[7,11,10],"to":[7.5,11.5,10.5],"faces":{"north":{"uv":[0,9,1,10],"texture":"#quartz_block"},"east":{"uv":[0,9,1,10],"texture":"#quartz_block"},"south":{"uv":[0,9,1,10],"texture":"#quartz_block"},"up":{"uv":[0,9,1,10],"texture":"#quartz_block"}}},{"from":[8.5,11,10],"to":[9,11.5,10.5],"faces":{"north":{"uv":[0,9,1,10],"texture":"#quartz_block"},"south":{"uv":[0,9,1,10],"texture":"#quartz_block"},"west":{"uv":[0,9,1,10],"texture":"#quartz_block"},"up":{"uv":[0,9,1,10],"texture":"#quartz_block"}}},{"from":[8.5,10,10.5],"to":[9,10.5,11],"faces":{"north":{"uv":[0,9,1,10],"texture":"#quartz_block"},"south":{"uv":[0,9,1,10],"texture":"#quartz_block"},"up":{"uv":[0,9,1,10],"texture":"#quartz_block"}}},{"from":[7,10,10.5],"to":[7.5,10.5,11],"faces":{"north":{"uv":[0,9,1,10],"texture":"#quartz_block"},"south":{"uv":[0,9,1,10],"texture":"#quartz_block"},"up":{"uv":[0,9,1,10],"texture":"#quartz_block"}}},{"from":[5,1,10],"to":[7,2.5,10.5],"faces":{"north":{"uv":[0,9,1,10],"texture":"#stone_stab"},"south":{"uv":[0,9,1,10],"texture":"#stone_stab"},"west":{"uv":[0,9,1,10],"texture":"#stone_stab"},"down":{"uv":[0,9,1,10],"texture":"#stone_stab"}}},{"from":[9,1,10],"to":[11,2.5,10.5],"faces":{"north":{"uv":[0,9,1,10],"texture":"#stone_stab"},"east":{"uv":[0,9,1,10],"texture":"#stone_stab"},"south":{"uv":[0,9,1,10],"texture":"#stone_stab"},"down":{"uv":[0,9,1,10],"texture":"#stone_stab"}}},{"from":[7,1,10],"to":[9,3,10.5],"faces":{"north":{"uv":[0,9,1,10],"texture":"#quartz_block"},"south":{"uv":[0,9,1,10],"texture":"#quartz_block"},"up":{"uv":[0,9,1,10],"texture":"#quartz_block"},"down":{"uv":[0,9,1,10],"texture":"#quartz_block"}}},{"from":[7.5,5.5,10],"to":[8.5,6.5,11],"faces":{"north":{"uv":[0,9,1,10],"texture":"#stone_stab"},"east":{"uv":[0,9,1,10],"texture":"#stone_stab"},"south":{"uv":[0,9,1,10],"texture":"#stone_stab"},"west":{"uv":[0,9,1,10],"texture":"#stone_stab"},"up":{"uv":[0,9,1,10],"texture":"#stone_stab"},"down":{"uv":[0,9,1,10],"texture":"#stone_stab"}}},{"from":[8.5,5.5,10.5],"to":[9,6.5,11],"faces":{"north":{"uv":[7,9.5,7.5,10.5],"texture":"#hardened_clay_blue"},"south":{"uv":[8.5,9.5,9,10.5],"texture":"#hardened_clay_blue"}}},{"from":[7,5.5,10.5],"to":[7.5,6.5,11],"faces":{"north":{"uv":[8.5,9.5,9,10.5],"texture":"#hardened_clay_blue"},"south":{"uv":[7,9.5,7.5,10.5],"texture":"#hardened_clay_blue"}}},{"from":[9,2.5,10],"to":[11,3,11],"faces":{"north":{"uv":[0,9,1,10],"texture":"#coal_block"},"east":{"uv":[0,9,1,10],"texture":"#coal_block"},"south":{"uv":[0,9,1,10],"texture":"#coal_block"},"west":{"uv":[0,9,1,10],"texture":"#coal_block"},"down":{"uv":[0,9,1,10],"texture":"#coal_block"}}},{"from":[5,2.5,10],"to":[7,3,11],"faces":{"north":{"uv":[0,9,1,10],"texture":"#coal_block"},"east":{"uv":[0,9,1,10],"texture":"#coal_block"},"south":{"uv":[0,9,1,10],"texture":"#coal_block"},"west":{"uv":[0,9,1,10],"texture":"#coal_block"},"down":{"uv":[0,9,1,10],"texture":"#coal_block"}}},{"from":[5,1,10.5],"to":[5.5,2.5,11],"faces":{"east":{"uv":[0,9,1,10],"texture":"#stone_stab"},"south":{"uv":[0,9,1,10],"texture":"#stone_stab"},"west":{"uv":[0,9,1,10],"texture":"#stone_stab"},"down":{"uv":[0,9,1,10],"texture":"#stone_stab"}}},{"from":[10.5,1,10.5],"to":[11,2.5,11],"faces":{"east":{"uv":[0,9,1,10],"texture":"#stone_stab"},"south":{"uv":[0,9,1,10],"texture":"#stone_stab"},"west":{"uv":[0,9,1,10],"texture":"#stone_stab"},"down":{"uv":[0,9,1,10],"texture":"#stone_stab"}}},{"from":[6,1,10.5],"to":[6.5,2.5,11],"faces":{"east":{"uv":[0,9,1,10],"texture":"#stone_stab"},"south":{"uv":[0,9,1,10],"texture":"#stone_stab"},"west":{"uv":[0,9,1,10],"texture":"#stone_stab"},"down":{"uv":[0,9,1,10],"texture":"#stone_stab"}}},{"from":[9.5,1,10.5],"to":[10,2.5,11],"faces":{"east":{"uv":[0,9,1,10],"texture":"#stone_stab"},"south":{"uv":[0,9,1,10],"texture":"#stone_stab"},"west":{"uv":[0,9,1,10],"texture":"#stone_stab"},"down":{"uv":[0,9,1,10],"texture":"#stone_stab"}}},{"from":[-5.5,8,10],"to":[4,8.5,10.5],"faces":{"north":{"uv":[0,9,1,10],"texture":"#wool_lime"},"south":{"uv":[0,9,1,10],"texture":"#wool_lime"}}},{"from":[12,8,10],"to":[21.5,8.5,10.5],"faces":{"north":{"uv":[0,9,1,10],"texture":"#wool_lime"},"south":{"uv":[0,9,1,10],"texture":"#wool_lime"}}},{"from":[3.5,8.5,10],"to":[4,9.5,10.5],"faces":{"north":{"uv":[0,9,1,10],"texture":"#quartz_block"},"south":{"uv":[0,9,1,10],"texture":"#quartz_block"}}},{"from":[3,10.5,10],"to":[3.5,11,10.5],"faces":{"north":{"uv":[0,9,1,10],"texture":"#quartz_block"},"south":{"uv":[0,9,1,10],"texture":"#quartz_block"},"up":{"uv":[0,9,1,10],"texture":"#quartz_block"}}},{"from":[2,9.5,10],"to":[3,10.5,10.5],"faces":{"north":{"uv":[0,9,1,10],"texture":"#quartz_block"},"south":{"uv":[0,9,1,10],"texture":"#quartz_block"}}},{"from":[1.5,8.5,10],"to":[2.5,9.5,10.5],"faces":{"north":{"uv":[0,9,1,10],"texture":"#quartz_block"},"south":{"uv":[0,9,1,10],"texture":"#quartz_block"}}},{"from":[0.5,8.5,10],"to":[1.5,9.5,10.5],"faces":{"north":{"uv":[0,9,1,10],"texture":"#hardened_clay_red"},"south":{"uv":[0,9,1,10],"texture":"#hardened_clay_red"}}},{"from":[2.5,10.5,10],"to":[3,11,10.5],"faces":{"north":{"uv":[0,9,1,10],"texture":"#quartz_block"},"south":{"uv":[0,9,1,10],"texture":"#quartz_block"},"up":{"uv":[0,9,1,10],"texture":"#quartz_block"}}},{"from":[1,9.5,10],"to":[2,10.5,10.5],"faces":{"north":{"uv":[0,9,1,10],"texture":"#hardened_clay_red"},"south":{"uv":[0,9,1,10],"texture":"#hardened_clay_red"},"up":{"uv":[0,9,1,10],"texture":"#hardened_clay_red"}}},{"from":[1.5,10.5,10],"to":[2.5,11,10.5],"faces":{"north":{"uv":[0,9,1,10],"texture":"#hardened_clay_red"},"south":{"uv":[0,9,1,10],"texture":"#hardened_clay_red"},"west":{"uv":[0,9,1,10],"texture":"#hardened_clay_red"},"up":{"uv":[0,9,1,10],"texture":"#hardened_clay_red"}}},{"from":[-0.5,8.5,10],"to":[0.5,9.5,10.5],"faces":{"north":{"uv":[0,9,1,10],"texture":"#quartz_block"},"south":{"uv":[0,9,1,10],"texture":"#quartz_block"}}},{"from":[0,9.5,10],"to":[1,10.5,10.5],"faces":{"north":{"uv":[0,9,1,10],"texture":"#quartz_block"},"south":{"uv":[0,9,1,10],"texture":"#quartz_block"},"up":{"uv":[0,9,1,10],"texture":"#quartz_block"}}},{"from":[-1.5,8.5,10],"to":[-0.5,9.5,10.5],"faces":{"north":{"uv":[0,9,1,10],"texture":"#hardened_clay_red"},"south":{"uv":[0,9,1,10],"texture":"#hardened_clay_red"}}},{"from":[-0.5,9.5,10],"to":[0,10.5,10.5],"faces":{"north":{"uv":[0,9,1,10],"texture":"#hardened_clay_red"},"south":{"uv":[0,9,1,10],"texture":"#hardened_clay_red"},"west":{"uv":[0,9,1,10],"texture":"#hardened_clay_red"},"up":{"uv":[0,9,1,10],"texture":"#hardened_clay_red"}}},{"from":[-3.5,8.5,10],"to":[-2.5,9.5,10.5],"faces":{"north":{"uv":[0,9,1,10],"texture":"#hardened_clay_red"},"south":{"uv":[0,9,1,10],"texture":"#hardened_clay_red"},"west":{"uv":[0,9,1,10],"texture":"#hardened_clay_red"},"up":{"uv":[0,9,1,10],"texture":"#hardened_clay_red"}}},{"from":[-4.5,8.5,10],"to":[-3.5,9,10.5],"faces":{"north":{"uv":[0,9,1,10],"texture":"#quartz_block"},"south":{"uv":[0,9,1,10],"texture":"#quartz_block"},"up":{"uv":[0,9,1,10],"texture":"#quartz_block"}}},{"from":[-2.5,8.5,10],"to":[-1.5,9.5,10.5],"faces":{"north":{"uv":[0,9,1,10],"texture":"#quartz_block"},"south":{"uv":[0,9,1,10],"texture":"#quartz_block"},"up":{"uv":[0,9,1,10],"texture":"#quartz_block"}}},{"from":[-2,9.5,10],"to":[-1,10,10.5],"faces":{"north":{"uv":[0,9,1,10],"texture":"#quartz_block"},"south":{"uv":[0,9,1,10],"texture":"#quartz_block"},"west":{"uv":[0,9,1,10],"texture":"#quartz_block"},"up":{"uv":[0,9,1,10],"texture":"#quartz_block"}}},{"from":[-1,9.5,10],"to":[-0.5,10,10.5],"faces":{"north":{"uv":[0,9,1,10],"texture":"#hardened_clay_red"},"south":{"uv":[0,9,1,10],"texture":"#hardened_clay_red"},"up":{"uv":[0,9,1,10],"texture":"#hardened_clay_red"}}},{"from":[-5.5,8.5,10],"to":[-4.5,9,10.5],"faces":{"north":{"uv":[0,9,1,10],"texture":"#hardened_clay_red"},"south":{"uv":[0,9,1,10],"texture":"#hardened_clay_red"},"up":{"uv":[0,9,1,10],"texture":"#hardened_clay_red"}}},{"from":[-1,4.5,10],"to":[4,8,10.5],"faces":{"north":{"uv":[12,8,16,11.5],"texture":"#hardened_clay_blue"},"east":{"uv":[5.5,8,6,11.5],"texture":"#hardened_clay_blue"},"south":{"uv":[0,8,4,11.5],"texture":"#hardened_clay_blue"},"west":{"uv":[10,8,10.5,11.5],"texture":"#hardened_clay_blue"},"down":{"uv":[0,5.5,4,6],"texture":"#hardened_clay_blue"}}},{"from":[-6.5,5,10],"to":[-5.5,9.5,10.5],"faces":{"north":{"uv":[0,9,1,10],"texture":"#wool_lime"},"east":{"uv":[0,9,1,10],"texture":"#wool_lime"},"south":{"uv":[0,9,1,10],"texture":"#wool_lime"},"west":{"uv":[0,9,1,10],"texture":"#wool_lime"},"up":{"uv":[0,9,1,10],"texture":"#wool_lime"},"down":{"uv":[0,9,1,10],"texture":"#wool_lime"}}},{"from":[12,4.5,10],"to":[17,8,10.5],"faces":{"north":{"uv":[0,8,4,11.5],"texture":"#hardened_clay_blue"},"east":{"uv":[5.5,8,6,11.5],"texture":"#hardened_clay_blue"},"south":{"uv":[12,8,16,11.5],"texture":"#hardened_clay_blue"},"west":{"uv":[10,8,10.5,11.5],"texture":"#hardened_clay_blue"},"down":{"uv":[12,5.5,16,6],"texture":"#hardened_clay_blue"}}},{"from":[17,5.5,10],"to":[21.5,8,10.5],"faces":{"north":{"uv":[10.5,8,15,10.5],"texture":"#hardened_clay_blue"},"south":{"uv":[1,8,5.5,10.5],"texture":"#hardened_clay_blue"},"down":{"uv":[1,5.5,5.5,6],"texture":"#hardened_clay_blue"}}},{"from":[21.5,5,10],"to":[22.5,9.5,10.5],"faces":{"north":{"uv":[0,9,1,10],"texture":"#wool_lime"},"east":{"uv":[0,9,1,10],"texture":"#wool_lime"},"south":{"uv":[0,9,1,10],"texture":"#wool_lime"},"west":{"uv":[0,9,1,10],"texture":"#wool_lime"},"up":{"uv":[0,9,1,10],"texture":"#wool_lime"},"down":{"uv":[0,9,1,10],"texture":"#wool_lime"}}},{"from":[17.5,8.5,10],"to":[18.5,9.5,10.5],"faces":{"north":{"uv":[0,9,1,10],"texture":"#quartz_block"},"south":{"uv":[0,9,1,10],"texture":"#quartz_block"},"up":{"uv":[0,9,1,10],"texture":"#quartz_block"}}},{"from":[16.5,8.5,10],"to":[17.5,9.5,10.5],"faces":{"north":{"uv":[0,9,1,10],"texture":"#hardened_clay_red"},"south":{"uv":[0,9,1,10],"texture":"#hardened_clay_red"}}},{"from":[14.5,8.5,10],"to":[15.5,9.5,10.5],"faces":{"north":{"uv":[0,9,1,10],"texture":"#hardened_clay_red"},"south":{"uv":[0,9,1,10],"texture":"#hardened_clay_red"}}},{"from":[19.5,8.5,10],"to":[20.5,9,10.5],"faces":{"north":{"uv":[0,9,1,10],"texture":"#quartz_block"},"south":{"uv":[0,9,1,10],"texture":"#quartz_block"},"up":{"uv":[0,9,1,10],"texture":"#quartz_block"}}},{"from":[15.5,8.5,10],"to":[16.5,9.5,10.5],"faces":{"north":{"uv":[0,9,1,10],"texture":"#quartz_block"},"south":{"uv":[0,9,1,10],"texture":"#quartz_block"}}},{"from":[20.5,8.5,10],"to":[21.5,9,10.5],"faces":{"north":{"uv":[0,9,1,10],"texture":"#hardened_clay_red"},"south":{"uv":[0,9,1,10],"texture":"#hardened_clay_red"},"up":{"uv":[0,9,1,10],"texture":"#hardened_clay_red"}}},{"from":[18.5,8.5,10],"to":[19.5,9.5,10.5],"faces":{"north":{"uv":[0,9,1,10],"texture":"#hardened_clay_red"},"east":{"uv":[0,9,1,10],"texture":"#hardened_clay_red"},"south":{"uv":[0,9,1,10],"texture":"#hardened_clay_red"},"up":{"uv":[0,9,1,10],"texture":"#hardened_clay_red"}}},{"from":[15,9.5,10],"to":[16,10.5,10.5],"faces":{"north":{"uv":[0,9,1,10],"texture":"#quartz_block"},"south":{"uv":[0,9,1,10],"texture":"#quartz_block"},"up":{"uv":[0,9,1,10],"texture":"#quartz_block"}}},{"from":[16,9.5,10],"to":[16.5,10.5,10.5],"faces":{"north":{"uv":[0,9,1,10],"texture":"#hardened_clay_red"},"east":{"uv":[0,9,1,10],"texture":"#hardened_clay_red"},"south":{"uv":[0,9,1,10],"texture":"#hardened_clay_red"},"up":{"uv":[0,9,1,10],"texture":"#hardened_clay_red"}}},{"from":[17,9.5,10],"to":[18,10,10.5],"faces":{"north":{"uv":[0,9,1,10],"texture":"#quartz_block"},"east":{"uv":[0,9,1,10],"texture":"#quartz_block"},"south":{"uv":[0,9,1,10],"texture":"#quartz_block"},"up":{"uv":[0,9,1,10],"texture":"#quartz_block"}}},{"from":[16.5,9.5,10],"to":[17,10,10.5],"faces":{"north":{"uv":[0,9,1,10],"texture":"#hardened_clay_red"},"south":{"uv":[0,9,1,10],"texture":"#hardened_clay_red"},"up":{"uv":[0,9,1,10],"texture":"#hardened_clay_red"}}},{"from":[14,9.5,10],"to":[15,10.5,10.5],"faces":{"north":{"uv":[0,9,1,10],"texture":"#hardened_clay_red"},"south":{"uv":[0,9,1,10],"texture":"#hardened_clay_red"},"up":{"uv":[0,9,1,10],"texture":"#hardened_clay_red"}}},{"from":[13.5,8.5,10],"to":[14.5,9.5,10.5],"faces":{"north":{"uv":[0,9,1,10],"texture":"#quartz_block"},"south":{"uv":[0,9,1,10],"texture":"#quartz_block"}}},{"from":[13.5,10.5,10],"to":[14.5,11,10.5],"faces":{"north":{"uv":[0,9,1,10],"texture":"#hardened_clay_red"},"east":{"uv":[0,9,1,10],"texture":"#hardened_clay_red"},"south":{"uv":[0,9,1,10],"texture":"#hardened_clay_red"},"up":{"uv":[0,9,1,10],"texture":"#hardened_clay_red"}}},{"from":[13,9.5,10],"to":[14,10.5,10.5],"faces":{"north":{"uv":[0,9,1,10],"texture":"#quartz_block"},"south":{"uv":[0,9,1,10],"texture":"#quartz_block"}}},{"from":[12.5,8.5,10],"to":[13.5,9.5,10.5],"faces":{"north":{"uv":[0,9,1,10],"texture":"#hardened_clay_red"},"south":{"uv":[0,9,1,10],"texture":"#hardened_clay_red"}}},{"from":[13,10.5,10],"to":[13.5,11,10.5],"faces":{"north":{"uv":[0,9,1,10],"texture":"#quartz_block"},"south":{"uv":[0,9,1,10],"texture":"#quartz_block"},"up":{"uv":[0,9,1,10],"texture":"#quartz_block"}}},{"from":[12,9.5,10],"to":[13,10.5,10.5],"faces":{"north":{"uv":[0,9,1,10],"texture":"#hardened_clay_red"},"south":{"uv":[0,9,1,10],"texture":"#hardened_clay_red"}}},{"from":[12.5,10.5,10],"to":[13,11,10.5],"faces":{"north":{"uv":[0,9,1,10],"texture":"#quartz_block"},"south":{"uv":[0,9,1,10],"texture":"#quartz_block"},"up":{"uv":[0,9,1,10],"texture":"#quartz_block"}}},{"from":[12,10.5,10],"to":[12.5,11.5,10.5],"faces":{"north":{"uv":[0,9,1,10],"texture":"#hardened_clay_red"},"east":{"uv":[0,9,1,10],"texture":"#hardened_clay_red"},"south":{"uv":[0,9,1,10],"texture":"#hardened_clay_red"},"west":{"uv":[0,9,1,10],"texture":"#hardened_clay_red"},"up":{"uv":[0,9,1,10],"texture":"#hardened_clay_red"}}},{"from":[12,8.5,10],"to":[12.5,9.5,10.5],"faces":{"north":{"uv":[0,9,1,10],"texture":"#quartz_block"},"south":{"uv":[0,9,1,10],"texture":"#quartz_block"}}},{"from":[9,9,11],"to":[11.5,10,11.5],"faces":{"east":{"uv":[0,9,1,10],"texture":"#wool_lime"},"south":{"uv":[0,9,1,10],"texture":"#wool_lime"},"west":{"uv":[0,9,1,10],"texture":"#wool_lime"},"up":{"uv":[0,9,1,10],"texture":"#wool_lime"},"down":{"uv":[0,9,1,10],"texture":"#wool_lime"}}},{"from":[4.5,9,11],"to":[7,10,11.5],"faces":{"east":{"uv":[0,9,1,10],"texture":"#wool_lime"},"south":{"uv":[0,9,1,10],"texture":"#wool_lime"},"west":{"uv":[0,9,1,10],"texture":"#wool_lime"},"up":{"uv":[0,9,1,10],"texture":"#wool_lime"},"down":{"uv":[0,9,1,10],"texture":"#wool_lime"}}}],"display":{"thirdperson_righthand":{"rotation":[69,0,0],"translation":[-6,-3.477,9.0434],"scale":[1.2,1.2,1.2]},"thirdperson_lefthand":{"rotation":[69,0,0],"translation":[-6,-3.477,9.0434],"scale":[1.2,1.2,1.2]},"firstperson_righthand":{"translation":[0,3.4782,0],"scale":[0.2,0.2,0.2]},"firstperson_lefthand":{"translation":[0,3.4782,0],"scale":[0.2,0.2,0.2]},"ground":{"translation":[0,1.3913,0],"scale":[0.2,0.2,0.2]},"gui":{"rotation":[-30,-16,0],"translation":[0,-0.695,0],"scale":[0.5,0.5,0.5]},"head":{"translation":[0,-13.21,0],"scale":[2,2,2]},"fixed":{"rotation":[0,180,0],"scale":[0.6,0.6,0.6]}}}